{
	"textures": {
		"0": "ssbrc:common/pokemon/pokemon/lapras/default",
		"particle": "minecraft:item/pufferfish"
	},
	"display": {
		"head": {
			"rotation": [0, 180, 0]
		}
	},
	"elements": [
		{
			"from": [7, 6.5, 5.5],
			"to": [14, 9.5, 10.5],
			"faces": {
				"north": {
					"uv": [10.9375, 0.75, 10.5, 1.125],
					"texture": "#0"
				},
				"east": {
					"uv": [11.25, 0.75, 10.9375, 1.125],
					"texture": "#0"
				},
				"south": {
					"uv": [11.6875, 0.75, 11.25, 1.125],
					"texture": "#0"
				},
				"west": {
					"uv": [10.5, 0.75, 10.1875, 1.125],
					"texture": "#0"
				},
				"up": {
					"uv": [10.5, 0.75, 10.9375, 0.125],
					"texture": "#0"
				},
				"down": {
					"uv": [10.9375, 0.125, 11.375, 0.75],
					"texture": "#0"
				}
			}
		},
		{
			"from": [6.99, 6.99, 5.49],
			"to": [14.01, 8.01, 10.51],
			"faces": {
				"north": {
					"uv": [13.8125, 0.625, 13.375, 0.75],
					"texture": "#0"
				},
				"east": {
					"uv": [14.125, 0.625, 13.8125, 0.75],
					"texture": "#0"
				},
				"south": {
					"uv": [14.5625, 0.625, 14.125, 0.75],
					"texture": "#0"
				},
				"west": {
					"uv": [13.375, 0.625, 13.0625, 0.75],
					"texture": "#0"
				},
				"up": {
					"uv": [13.375, 0.625, 13.8125, 0],
					"texture": "#0"
				},
				"down": {
					"uv": [13.8125, 0, 14.25, 0.625],
					"texture": "#0"
				}
			}
		}
	]
}